pymetaphone_br/__init__.py
pymetaphone_br/metaphone.py
pymetaphone_br-0.0.2.dist-info/LICENSE
pymetaphone_br-0.0.2.dist-info/METADATA
pymetaphone_br-0.0.2.dist-info/WHEEL
pymetaphone_br-0.0.2.dist-info/RECORD
